sleepyask/__init__.py
sleepyask/chat.py
sleepyask-7.1.0.dist-info/LICENSE
sleepyask-7.1.0.dist-info/METADATA
sleepyask-7.1.0.dist-info/WHEEL
sleepyask-7.1.0.dist-info/top_level.txt
sleepyask-7.1.0.dist-info/RECORD
